{"type":"FeatureCollection","features":[
  {"type": "Feature","properties":{
      "title": "United Kingdom",
      "description": "A northside park that is home to the Lincoln Park Zoo"
    },
    "geometry": {
      "coordinates": [-0.124614,51.499919],
      "type": "Point"
    }
  },
  {
    "type": "Feature","properties": {
      "title": "Mexico",
      "description": "A lakefront park on Chicago's south side"
    },
    "geometry": {
      "coordinates": [-99.133232,19.432686],
      "type": "Point"
    }
  },
  {
    "type": "Feature","properties": {
      "title": "Republic of Ireland",
      "description": "A downtown park known for its art installations and unique architecture"
    },
    "geometry": {
      "coordinates": [-6.26006,53.348923],
      "type": "Point"
    }
  }
]}
